<annotation>
	<folder>Drone-600x340-Dataset</folder>
	<filename>drone-55.jpg</filename>
	<path>C:\Users\Austi\Downloads\Junior Design\Drone-600x340-Dataset\drone-55.jpg</path>
	<source>
		<database>Unknown</database>
	</source>
	<size>
		<width>600</width>
		<height>338</height>
		<depth>3</depth>
	</size>
	<segmented>0</segmented>
	<object>
		<name>drone</name>
		<pose>Unspecified</pose>
		<truncated>0</truncated>
		<difficult>0</difficult>
		<bndbox>
			<xmin>52</xmin>
			<ymin>32</ymin>
			<xmax>225</xmax>
			<ymax>103</ymax>
		</bndbox>
	</object>
</annotation>
